cfml_kernel/__init__.py
cfml_kernel/box_wrapper.py
cfml_kernel/cfml/__init__.py
cfml_kernel/cfml/__main__.py
cfml_kernel/cfml/install.py
cfml_kernel/cfml/kernel.py
cfml_kernel/cfscript/__init__.py
cfml_kernel/cfscript/__main__.py
cfml_kernel/cfscript/install.py
cfml_kernel/cfscript/kernel.py
cfml_kernel-1.2.1.dist-info/LICENSE
cfml_kernel-1.2.1.dist-info/METADATA
cfml_kernel-1.2.1.dist-info/WHEEL
cfml_kernel-1.2.1.dist-info/top_level.txt
cfml_kernel-1.2.1.dist-info/RECORD
