Metadata-Version: 2.1
Name: cfml-kernel
Version: 1.2.1
Summary: A Jupyter notebook kernel for CFML powered by Commandbox
Author-email: Jason steinshouer <jason.steinshouer@gmail.com>
Classifier: Programming Language :: Python :: 3
Classifier: License :: OSI Approved :: MIT License
Classifier: Operating System :: OS Independent
Requires-Python: >=3.7
License-File: LICENSE
Requires-Dist: ipykernel
